multicast/__init__.py
multicast/__main__.py
multicast/env.py
multicast/exceptions.py
multicast/hear.py
multicast/recv.py
multicast/send.py
multicast/skt.py
multicast-2.0.8.data/scripts/__main__.py
multicast-2.0.8.dist-info/licenses/LICENSE.md
multicast-2.0.8.dist-info/METADATA
multicast-2.0.8.dist-info/WHEEL
multicast-2.0.8.dist-info/top_level.txt
multicast-2.0.8.dist-info/RECORD
