Metadata-Version: 2.4
Name: multicast
Version: 2.0.8
Summary: Multicast Python Module for Send/Recv Stubs.
Home-page: https://github.com/reactive-firewall/multicast
Download-URL: https://github.com/reactive-firewall/multicast.git
Author: Mr. Walls
Author-email: reactive-firewall@users.noreply.github.com
License-Expression: MIT
Project-URL: "Bug Tracker", https://github.com/reactive-firewall/multicast/issues
Project-URL: License, https://raw.githubusercontent.com/reactive-firewall/multicast/HEAD/LICENSE.md
Project-URL: Documentation, https://reactive-firewallmulticast.readthedocs.io/en/stable
Project-URL: Repository, https://github.com/reactive-firewall/multicast.git
Platform: any
Classifier: Development Status :: 5 - Production/Stable
Classifier: Environment :: Console
Classifier: Intended Audience :: Developers
Classifier: Operating System :: POSIX
Classifier: Operating System :: MacOS :: MacOS X
Classifier: Operating System :: POSIX :: Linux
Classifier: Programming Language :: Python :: 3
Classifier: Programming Language :: Python :: 3 :: Only
Classifier: Programming Language :: Python :: 3.13
Classifier: Programming Language :: Python :: 3.12
Classifier: Programming Language :: Python :: 3.11
Classifier: Programming Language :: Python :: 3.10
Classifier: Topic :: Software Development :: Libraries :: Python Modules
Classifier: Topic :: System :: Networking
Obsoletes: S
Obsoletes: e
Obsoletes: e
Requires-Python: !=3.14.*,!=3.9.10,!=3.9.11,!=3.9.12,!=3.9.13,!=3.9.14,!=3.9.15,!=3.9.16,!=3.9.17,!=3.9.18,!=3.9.19,!=3.9.7,!=3.9.8,>=3.9.6
License-File: LICENSE.md
Requires-Dist: setuptools>=75.0
Requires-Dist: pip>=24.3.1
Requires-Dist: build>=1.1.1
Requires-Dist: wheel>=0.44
Provides-Extra: testing
Requires-Dist: pytest>=7.4; extra == "testing"
Requires-Dist: pytest-checkdocs>=2.4; extra == "testing"
Requires-Dist: pytest-flake8>=1.0.7; extra == "testing"
Requires-Dist: coverage>=7; extra == "testing"
Requires-Dist: pytest-enabler>=1.0.1; extra == "testing"
Requires-Dist: flake8>=5.0; extra == "testing"
Requires-Dist: virtualenv>=20.26.6; extra == "testing"
Requires-Dist: wheel>=0.44.0; extra == "testing"
Requires-Dist: pip>=24.3.1; extra == "testing"
Requires-Dist: pytest-cov>=4.0.0; platform_python_implementation != "PyPy" and extra == "testing"
Dynamic: classifier
Dynamic: description
Dynamic: description-content-type
Dynamic: download-url
Dynamic: license
Dynamic: license-file
Dynamic: license-expression
Dynamic: obsoletes
Dynamic: requires-dist
